tkinterquickhelper/__init__.py
tkinterquickhelper/funcwin/__init__.py
tkinterquickhelper/funcwin/default_functions.py
tkinterquickhelper/funcwin/frame_function.py
tkinterquickhelper/funcwin/frame_params.py
tkinterquickhelper/funcwin/function_helper.py
tkinterquickhelper/funcwin/main_window.py
tkinterquickhelper/funcwin/patchs_windows.py
tkinterquickhelper/funcwin/project_ico.ico
tkinterquickhelper/funcwin/storing_functions.py
tkinterquickhelper/funcwin/tk_window.py
tkinterquickhelper-1.6.103.dist-info/LICENSE.txt
tkinterquickhelper-1.6.103.dist-info/METADATA
tkinterquickhelper-1.6.103.dist-info/WHEEL
tkinterquickhelper-1.6.103.dist-info/top_level.txt
tkinterquickhelper-1.6.103.dist-info/RECORD
