Metadata-Version: 2.1
Name: tkinterquickhelper
Version: 1.6.103
Summary: Helpers for tkinter, extra windows.
Home-page: http://www.xavierdupre.fr/app/tkinterquickhelper/helpsphinx/index.html
Author: Xavier Dupré
Author-email: xavier.dupre@gmail.com
License: MIT
Download-URL: https://github.com/sdpython/tkinterquickhelper
Keywords: tkinterquickhelper,tkinter,Xavier,Dupré
Platform: UNKNOWN
Classifier: Programming Language :: Python :: 3
Classifier: Intended Audience :: Developers
Classifier: Topic :: Scientific/Engineering
Classifier: Topic :: Education
Classifier: License :: OSI Approved :: MIT License
Classifier: Development Status :: 5 - Production/Stable
Requires-Dist: pyquickhelper
